{
  "name": "@decelerate/cruiseh",
  "version": "0.3.0",
  "license": "MIT",
  "exports": {
    ".": "./index.ts",
    "./router": "./router.ts",
    "./types": "./types.ts"
  },
  "publish": {
    "include": [
      "LICENSE",
      "README.md",
      "CONTRIBUTING.md",
      "deno.json",
      "index.ts",
      "router.ts",
      "types.ts",
      "utils.ts"
    ]
  },
  "tasks": {
    "check": "deno check router.ts types.ts utils/"
  },
  "fmt": {
    "exclude": [
      "README.md"
    ]
  },
  "lock": false
}
